{
  "title": "Humanity - Complete Timeline",
  "author": "marsresident / Van Kush Family",
  "period": "2016 (STEEM Era)",
  "source": "Steemit Post - steemit.com/earth/@marsresident",
  "overview": "Comprehensive timeline of human history from 100,000 years ago to modern era, covering religion, technology, civilization, and discovery",

  "key_corrections": {
    "language_fire": "NOT created by our species - language through gestures existed longer, fire control 1M+ years",
    "neanderthal_dna": "1-4% in most humans, except Sub-Saharan Africans (100% Homo Sapien)",
    "denisovan_dna": "4-6% only in Papua New Guinea natives"
  },

  "prehistoric_milestones": {
    "70000_bc": {
      "event": "First human rituals",
      "location": "Python Cave, Tsodilo Hills, Botswana",
      "people": "San people (still live there today)",
      "artifacts": "Stone carved like python scales, 13,000 tools",
      "significance": "Proof of abstract thought 70,000 years ago"
    },
    "50000_bc": {
      "event": "Symbolic thought and raw material selection spread",
      "evidence": ["Diepkloof Ostrich egg carvings", "Blombos Cave"],
      "inventions": "First bedding (Imphepho plant)",
      "herbs": "Silene Udulata (dream herb for Ubulawu mixture)"
    },
    "45000_bc": {
      "event": "Southern Dispersal Route - Africa to Australia",
      "route": "Southern Africa → Ethiopia/Saudi Arabia → India → Indochina → Australia",
      "food": "Seafood critical along route"
    },
    "30000_bc": {
      "event": "First paintings ever",
      "location": "Bhimbetka Rock Shelters, Madhya Pradesh, India",
      "related_sites": "700 similar sites found"
    },
    "18000_45000_bc": {
      "location": "Lake Mungo, Australia",
      "significance": "Oldest cremation example, Dreamtime religion origins",
      "note": "Dreaming = 'time out of time' or 'everywhen'"
    },
    "35000_bc": {
      "events": ["First dogs domesticated (4 strains)", "Japan-Dolphin fishing cooperation"],
      "dog_strains": ["Asian Dogs", "Carolina Dogs", "Dingos", "Singing Dogs"]
    }
  },

  "agricultural_civilization": {
    "11000_bc": {
      "event": "First plant farmed - Fig tree",
      "location": "Gesher, near West Bank/Jordan border",
      "method": "Human pollination instead of Fig wasps"
    },
    "10000_bc": {
      "events": [
        "Native Americans cross Siberia to Alaska",
        "Nabta Playa (Egypt/Kemet) - first star mapping",
        "Throwing stick → boomerang transition",
        "City of Dwarka built (India, now underwater)"
      ],
      "scarab_note": "Scarab beetles follow Moon/Stars, may have helped star mapping"
    },
    "5000_bc": {
      "event": "Farming meets Hunter-Gatherer trade",
      "location": "Dabki, Poland",
      "evidence": "Funnel Beaker culture pottery"
    },
    "4000_bc": {
      "event": "First mass production of Wine",
      "location": "Armenia"
    },
    "3500_bc": {
      "event": "Horses domesticated",
      "location": "Kazakhstan to Armenia",
      "people": "Botai people"
    },
    "3000_bc": {
      "event": "First wheel invented",
      "location": "Sumeria",
      "significance": "Became religious symbol (spokes, movement = celestial bodies)"
    }
  },

  "ancient_civilizations": {
    "calendar_creation": {
      "method": "Walls as fake horizons, mark sun position daily = 365 marks",
      "months": "Moon cycles = 12 Moon-ths",
      "days": "Saturn-day, Sun-day, Moon-day from Ogdoad (7 heavenly bodies)"
    },
    "2600_bc": {
      "figure": "Imhotep",
      "inventions": ["Medicine", "Surgery", "Stairs", "Columns", "Step Pyramid"],
      "legacy": "Temple became first Hospital, later worshiped as God"
    },
    "3300_1700_bc": {
      "civilization": "Indus Valley",
      "significance": "Precursor to Hinduism, first grid-shaped city"
    },
    "2000_bc": {
      "location": "Crete",
      "significance": "Mediterranean mixing of Egyptian, Eurasian, European cultures"
    },
    "1800_bc": "Babylon created and expanded",
    "1500_bc": {
      "events": [
        "Vedas written in Sanskrit (Rig Veda first) → Hinduism",
        "Greek culture appears",
        "Phoenicia founded (Israel, Lebanon, Jordan, Palestine, Syria)"
      ],
      "phoenician_inventions": ["Tyrian Purple dye", "Advanced boats", "Clear glass", "Languages"],
      "note": "Word 'Europe' from Phoenician Goddess Europa"
    }
  },

  "classical_era": {
    "800_bc": {
      "event": "Carthage founded",
      "founder": "Queen Dido (Phoenician/Punic)",
      "location": "North Africa (Tunisia, Libya, Morocco, Algeria)",
      "also": "Zoroaster creates Zoroastrianism - first monotheism"
    },
    "782_bc": "Yerevan founded (Armenia capital)",
    "753_bc": "Rome founded",
    "500_bc": {
      "events": ["Siddhartha becomes Buddha", "Persian Empire established by Cyrus"]
    },
    "300_bc": {
      "figures": ["Philip II (Macedonia)", "Alexander the Great"],
      "significance": "Hellenistic Era - East meets West",
      "key_books": ["Aegyptiaca by Manethos", "Babyloniaca by Berosus"],
      "institutions": "Library of Alexandria, first Musaeum"
    },
    "200_bc": {
      "event": "Punic Wars (Rome vs Carthage)",
      "key_figure": "Hannibal Barca - taught Rome military tactics"
    },
    "196_bc": "Rosetta Stone created",
    "100_bc": "Cicero transforms Politics and Democracy",
    "27_bc": "Roman Empire founded",
    "0_ad": "Jesus challenges Rome, killed",
    "64_ad": "Rome burns, Nero plays fiddle"
  },

  "medieval_to_modern": {
    "300_ad": "Constantine - first Christian Roman Emperor ('In this sign you conquer')",
    "330_ad": "Constantinople founded (now Istanbul)",
    "600_ad": {
      "event": "Mohammed composes Quran",
      "significance": "Mosques become knowledge/science centers",
      "contributions": "Al- words: Alchemy, Alcohol, Algebra"
    },
    "1000_ad": {
      "events": ["Hashashins (Assassins) formed", "Poor Knights of Christ → Knights Templar", "Crusades"]
    },
    "1215_ad": {
      "event": "Magna Carta signed",
      "significance": "Juries, Rights, Parliaments - power from Kings to people"
    },
    "1400_ad": "Leonardo Da Vinci (Tank, Helicopter, Scuba blueprints)",
    "1492_ad": "Columbus sails to America"
  },

  "scientific_revolution": {
    "1600_ad": "Galileo maps sky with telescope",
    "newton": "Discovers gravity",
    "1698_ad": "Steam engine invented",
    "1700_ad": "Electronic devices begin, Galvani discovers bioelectricity",
    "1776_ad": "American Declaration of Independence (Jefferson + Bannecker)",
    "1799_ad": "Volta discovers electrolytes, first battery",
    "1820_1830_ad": "Electromagnetic engines, Faraday's law",
    "1837_ad": "Stein Hill - Earth as circuit proposal",
    "1839_ad": "Becquerel discovers photovoltaics (solar power)",
    "1840_ad": "Telegraph and Morse Code",
    "1858_ad": "Transatlantic cable",
    "1863_ad": "Emancipation Proclamation",
    "1879_ad": "Edison - lightbulb, fuses, microphones",
    "1886_1900_ad": {
      "figure": "Nikola Tesla",
      "inventions": ["AC", "Rotating Electric Field", "Radio", "Wireless transmission", "Tesla Coil"],
      "connection": "Friends with Swami Vivekananda (first Hindu Temples in US)"
    },
    "1890_ad": "Steinmetz → General Electric foundation",
    "1903_ad": "Wright Brothers - first airplane",
    "1908_ad": "Ford Model T",
    "1905_1939_ad": "Einstein's theories",
    "1914_1918_ad": "WWI splits Ottoman Empire",
    "1920_ad": "Marcus Garvey (Black Pride), Noble Drew Ali (Moorish Science Temple)",
    "1927_ad": "Farnsworth - first electronic television",
    "1939_1945_ad": "WWII, only atomic bomb used in war"
  },

  "cryptology_integration": {
    "lesson_modules": [
      "prehistoric_humanity",
      "ancient_civilizations",
      "scientific_revolution",
      "cultural_transmission"
    ],
    "quiz_questions": [
      {
        "q": "Where is the oldest evidence of human rituals?",
        "a": "Python Cave, Tsodilo Hills, Botswana - 70,000 years ago by San people",
        "explanation": "Stone carved like python scales, 13,000 tools"
      },
      {
        "q": "What was the first plant ever farmed?",
        "a": "Fig tree - 11,000 BC at Gesher near West Bank/Jordan",
        "explanation": "Humans learned to pollinate like fig wasps"
      },
      {
        "q": "What did Imhotep invent?",
        "a": "Medicine, Surgery, Stairs, Columns, and the Step Pyramid (2600 BC)",
        "explanation": "His temple became first Hospital, later worshiped as God"
      },
      {
        "q": "What's special about India according to @marsresident?",
        "a": "Only large civilization still practicing same Ancient Religion with same Ancient Temples",
        "explanation": "Hinduism has unbroken continuity"
      },
      {
        "q": "What did Tesla and Swami Vivekananda have in common?",
        "a": "They were friends - Vivekananda brought first Hindu Temples to US in same era",
        "explanation": "East-West spiritual-scientific connection"
      }
    ],
    "achievement_unlocks": [
      "Prehistory Scholar: Know the 70,000 year timeline",
      "Civilization Mapper: Understand rise of ancient cultures",
      "Scientific Revolution Student: Know Tesla, Edison, Einstein era",
      "Cultural Transmitter: See how knowledge flows across civilizations"
    ]
  },

  "van_kush_connection": {
    "author": "marsresident is Van Kush Family STEEM account",
    "relevance": "Deep historical context for understanding human potential",
    "application": "Van Kush traces lineages and cultural transmissions",
    "philosophy": "Understanding our full history empowers our future"
  }
}
